MANIFEST.in
README.md
pyproject.toml
setup.cfg
setup.py
BioExt/__init__.py
BioExt/align/__init__.py
BioExt/align/_align.c
BioExt/align/_align.cpython-311-darwin.so
BioExt/align/_align.cpython-312-darwin.so
BioExt/align/_align.cpython-314-darwin.so
BioExt/align/_align.cpython-39-darwin.so
BioExt/align/_align.pyx
BioExt/align/alignment.c
BioExt/align/alignment.h
BioExt/align/__pycache__/__init__.cpython-311.pyc
BioExt/align/__pycache__/__init__.cpython-312.pyc
BioExt/align/__pycache__/__init__.cpython-314.pyc
BioExt/align/__pycache__/__init__.cpython-39.pyc
BioExt/args/__init__.py
BioExt/collections/__init__.py
BioExt/collections/_counter.py
BioExt/collections/_ordereddict.py
BioExt/data/fonts/ttf/Roboto-Black.ttf
BioExt/data/fonts/ttf/Roboto-BlackItalic.ttf
BioExt/data/fonts/ttf/Roboto-Bold.ttf
BioExt/data/fonts/ttf/Roboto-BoldCondensed.ttf
BioExt/data/fonts/ttf/Roboto-BoldCondensedItalic.ttf
BioExt/data/fonts/ttf/Roboto-BoldItalic.ttf
BioExt/data/fonts/ttf/Roboto-Condensed.ttf
BioExt/data/fonts/ttf/Roboto-CondensedItalic.ttf
BioExt/data/fonts/ttf/Roboto-Italic.ttf
BioExt/data/fonts/ttf/Roboto-Light.ttf
BioExt/data/fonts/ttf/Roboto-LightItalic.ttf
BioExt/data/fonts/ttf/Roboto-Medium.ttf
BioExt/data/fonts/ttf/Roboto-MediumItalic.ttf
BioExt/data/fonts/ttf/Roboto-Regular.ttf
BioExt/data/fonts/ttf/Roboto-Thin.ttf
BioExt/data/fonts/ttf/Roboto-ThinItalic.ttf
BioExt/data/references/cov2/CoV2-E.fa
BioExt/data/references/cov2/CoV2-M.fa
BioExt/data/references/cov2/CoV2-N.fa
BioExt/data/references/cov2/CoV2-ORF10.fa
BioExt/data/references/cov2/CoV2-ORF1a.fa
BioExt/data/references/cov2/CoV2-ORF1b.fa
BioExt/data/references/cov2/CoV2-ORF3a.fa
BioExt/data/references/cov2/CoV2-ORF5.fa
BioExt/data/references/cov2/CoV2-ORF6.fa
BioExt/data/references/cov2/CoV2-ORF7a.fa
BioExt/data/references/cov2/CoV2-ORF7b.fa
BioExt/data/references/cov2/CoV2-ORF8.fa
BioExt/data/references/cov2/CoV2-RdRp.fa
BioExt/data/references/cov2/CoV2-S.fa
BioExt/data/references/cov2/CoV2-endornase.fa
bioext.egg-info/PKG-INFO
bioext.egg-info/SOURCES.txt
bioext.egg-info/dependency_links.txt
bioext.egg-info/requires.txt
bioext.egg-info/top_level.txt
