Metadata-Version: 2.4
Name: bioext
Version: 0.21.10
Summary: Misc utilities and definitions not included or hidden in BioPython
Home-page: http://github.com/veg/bioext
Author: N Lance Hepler
Author-email: nlhepler@gmail.com
License: GNU GPL version 3
Requires-Python: >=3.10
Requires-Dist: biopython>=1.78
Requires-Dist: numpy>=2.0
Requires-Dist: scipy>=0.15
Requires-Dist: pysam>=0.17
Requires-Dist: joblib
Requires-Dist: six
Dynamic: author
Dynamic: author-email
Dynamic: home-page
Dynamic: license
Dynamic: requires-dist
Dynamic: requires-python
Dynamic: summary
